PDSUtilities/__init__.py
PDSUtilities/version.py
PDSUtilities/ipywidgets/__init__.py
PDSUtilities/ipywidgets/prev_dropdown_next.py
PDSUtilities/pandas/__init__.py
PDSUtilities/pandas/plot_correlation_matrix.py
PDSUtilities/pandas/plot_correlation_scatter.py
PDSUtilities/pandas/plot_correlation_triangle.py
PDSUtilities/pandas/plot_histograms.py
PDSUtilities/pandas/plot_parallel_categories.py
PDSUtilities/pandas/plot_parallel_coordinates.py
PDSUtilities/pandas/utilities.py
PDSUtilities/plotly/ColorblindSafeColormaps.py
PDSUtilities/plotly/__init__.py
PDSUtilities/plotly/create_image_subplots.py
PDSUtilities/plotly/get_specs_from_mosaic.py
PDSUtilities/plotly/templates.py
PDSUtilities/plotly/utilities.py
PDSUtilities/tensorflow/SequentialWithConcatenations.py
PDSUtilities/tensorflow/__init__.py
PDSUtilities/tensorflow/plot_history.py
PDSUtilities/tensorflow/tvp_split.py
PDSUtilities/tensorflow/view_model.py
PDSUtilities/xgboost/__init__.py
PDSUtilities/xgboost/plot_importance.py
PDSUtilities/xgboost/plot_tree.py
PDSUtilities-0.1.26.dist-info/LICENSE
PDSUtilities-0.1.26.dist-info/METADATA
PDSUtilities-0.1.26.dist-info/WHEEL
PDSUtilities-0.1.26.dist-info/top_level.txt
PDSUtilities-0.1.26.dist-info/RECORD
