Metadata-Version: 2.1
Name: PDSUtilities
Version: 0.1.26
Summary: Utilities for data science in python
Home-page: https://github.com/DrJohnWagner/PDSUtilities
Author: Dr. John Wagner
Author-email: Dr.John.Wagner@gmail.com
License: Apache-2.0
Platform: UNKNOWN
License-File: LICENSE
Requires-Dist: igraph
Requires-Dist: ipywidgets
Requires-Dist: nbformat
Requires-Dist: numpy
Requires-Dist: pandas
Requires-Dist: plotly
Requires-Dist: tensorflow
Requires-Dist: xgboost
